[{"date": "20240123200855", "mission": "GalaxyOne", "device": "Satelite", "state": "excellent", "hash": 8551762585140592492}, {"date": "20240123200855", "mission": "GalaxyOne", "device": "Nave", "state": "excellent", "hash": 3361773325702648789}, {"date": "20240123200855", "mission": "GalaxyOne", "device": "Traje", "state": "unknown", "hash": 1365201131755024896}, {"date": "20240123200855", "mission": "GalaxyOne", "device": "Vehiculo", "state": "falty", "hash": -2364803092467464168}, {"date": "20240123200855", "mission": "GalaxyOne", "device": "Robot", "state": "warning", "hash": 1510953432664094296}]