[{"date": "20240122142111", "mission": "OrbitOne", "device": "Satelite", "state": "warning", "hash": -4422603812162119935}, {"date": "20240122142111", "mission": "OrbitOne", "device": "Nave", "state": "excellent", "hash": -1823565711996087299}, {"date": "20240122142111", "mission": "OrbitOne", "device": "Traje", "state": "unknown", "hash": 4054410342806045243}, {"date": "20240122142111", "mission": "OrbitOne", "device": "Vehiculo", "state": "killed", "hash": 7447656085014147580}, {"date": "20240122142111", "mission": "OrbitOne", "device": "Robot", "state": "unknown", "hash": 3492328324947392265}]